astro_pics/.DS_Store
astro_pics/__init__.py
astro_pics/fits2png.py
astro_pics/main.py
astro_pics-1.1.1.dist-info/METADATA
astro_pics-1.1.1.dist-info/WHEEL
astro_pics-1.1.1.dist-info/licenses/LICENSE
astro_pics-1.1.1.dist-info/RECORD
