Metadata-Version: 2.1
Name: astro_pics
Version: 1.1.1
Summary: Project for editing images of astronomical objects
Project-URL: Homepage, https://github.com/Aromik/image_modify_astro
Project-URL: Bug Tracker, https://github.com/Aromik/image_modify_astro/issues
Author-email: Aromik <mr.aromik@gmail.com>
License: Copyright (c) 2018 The Python Packaging Authority
License-File: LICENSE
Classifier: License :: OSI Approved :: MIT License
Classifier: Operating System :: OS Independent
Classifier: Programming Language :: Python :: 3
Requires-Python: >=3.7
